{"cameraMode":{"drawMode":0,"name":"Shaded","section":"Shading Mode"},"sceneLighting":true,"audioPlay":false,"sceneViewState":{"m_AlwaysRefresh":false,"showFog":true,"showSkybox":true,"showFlares":true,"showImageEffects":true,"showParticleSystems":true,"showVisualEffectGraphs":true,"m_FxEnabled":true},"in2DMode":false,"pivot":{"x":7.046180248260498,"y":0.9491872191429138,"z":6.754668235778809},"rotation":{"x":-0.17981618642807008,"y":0.8014123439788818,"z":-0.29507166147232058,"w":-0.4882502555847168},"size":4.268955230712891,"orthographic":false}